gordian/config.py
gordian/gordian.py
gordian/repo.py
gordian/transformations.py
gordian/files/__init__.py
gordian/files/base_file.py
gordian/files/changelog_file.py
gordian/files/json_file.py
gordian/files/markdown_file.py
gordian/files/plaintext_file.py
gordian/files/yaml_file.py
gordian-3.8.1.dist-info/licenses/LICENSE
gordian-3.8.1.dist-info/METADATA
gordian-3.8.1.dist-info/WHEEL
gordian-3.8.1.dist-info/entry_points.txt
gordian-3.8.1.dist-info/top_level.txt
gordian-3.8.1.dist-info/RECORD
