Metadata-Version: 2.4
Name: gordian
Version: 3.8.1
Summary: A tool to search and replace files in a Git repo
Home-page: https://github.com/argoproj-labs/gordian
Author: Intuit
Author-email: cg-sre@intuit.com
License-File: LICENSE
Requires-Dist: pygithub<2.6.1
Requires-Dist: pyyaml
Requires-Dist: jsonpatch
Requires-Dist: deepdiff
Requires-Dist: retry
Provides-Extra: test
Requires-Dist: pytest; extra == "test"
Requires-Dist: pytest-cov; extra == "test"
Requires-Dist: pytest-runner; extra == "test"
Requires-Dist: flake8; extra == "test"
Dynamic: author
Dynamic: author-email
Dynamic: description
Dynamic: description-content-type
Dynamic: home-page
Dynamic: license-file
Dynamic: provides-extra
Dynamic: requires-dist
Dynamic: summary
